babeljs/__init__.py
babeljs/apps.py
babeljs/conf.py
babeljs/version.py
babeljs/execjs/__init__.py
babeljs/execjs/__main__.py
babeljs/execjs/exceptions.py
babeljs/execjs/runtime.py
babeljs/execjs/utils.py
babeljs/static/babeljs/browser-5.8.33.js
babeljs/static/babeljs/browser-5.8.33.min.js
babeljs/templatetags/__init__.py
babeljs/templatetags/babeljs.py
django_babeljs-0.2.dist-info/DESCRIPTION.rst
django_babeljs-0.2.dist-info/METADATA
django_babeljs-0.2.dist-info/RECORD
django_babeljs-0.2.dist-info/WHEEL
django_babeljs-0.2.dist-info/metadata.json
django_babeljs-0.2.dist-info/top_level.txt
