Metadata-Version: 2.0
Name: django-babeljs
Version: 0.2
Summary: Integrate babeljs with django
Home-page: https://bitbucket.org/rsalmaso/django-babeljs
Author: Raffaele Salmaso
Author-email: raffaele@salmaso.org
License: MIT
Platform: UNKNOWN
Classifier: Development Status :: 5 - Production/Stable
Classifier: Intended Audience :: Developers
Classifier: Natural Language :: English
Classifier: License :: OSI Approved :: MIT License
Classifier: Programming Language :: Python
Classifier: Programming Language :: Python :: 3
Classifier: Programming Language :: Python :: 3.4
Classifier: Programming Language :: Python :: 3.5
Classifier: Programming Language :: Python :: 3.6
Classifier: Programming Language :: JavaScript
Requires-Dist: django
